pygvariant/GVariantConverter.py
pygvariant/GVariantParser.py
pygvariant/GVariantSerializer.py
pygvariant/__init__.py
pygvariant-0.4.0.dist-info/licenses/LICENSE.md
pygvariant-0.4.0.dist-info/METADATA
pygvariant-0.4.0.dist-info/WHEEL
pygvariant-0.4.0.dist-info/top_level.txt
pygvariant-0.4.0.dist-info/RECORD
