Metadata-Version: 2.4
Name: pygvariant
Version: 0.4.0
Summary: A library to serialize and deserialize gvariant values in gschema files.
Author-email: Samuel Coles <me@smurf.codes>
License: Copyright 2026 Samuel Coles <me [at] smurf.codes>
Project-URL: Homepage, https://github.com/smurf/pygvariant
Project-URL: Issues, https://github.com/smurf/pygvariant/issues
Classifier: Programming Language :: Python :: 3
Classifier: Operating System :: OS Independent
Requires-Python: >=3.11
License-File: LICENSE.md
Dynamic: license-file
